meghana_hello_world/__init__.py
meghana_hello_world/cli.py
meghana_hello_world-0.5.dist-info/LICENSE
meghana_hello_world-0.5.dist-info/METADATA
meghana_hello_world-0.5.dist-info/WHEEL
meghana_hello_world-0.5.dist-info/entry_points.txt
meghana_hello_world-0.5.dist-info/top_level.txt
meghana_hello_world-0.5.dist-info/RECORD
