Metadata-Version: 2.1
Name: meghana_hello_world
Version: 0.5
Summary: A simple Hello World package with addition
Author: meghana
Author-email: meghanabl2112@gmail.com
License-File: LICENSE
Requires-Dist: click
